debio/__init__.py
debio/api.py
debio/cli.py
debio/py.typed
debio/version.py
debio/resources/__init__.py
debio/resources/properties.json
debio/resources/terms.json
debio/resources/typedefs.json
debio-0.1.1.dist-info/LICENSE
debio-0.1.1.dist-info/METADATA
debio-0.1.1.dist-info/WHEEL
debio-0.1.1.dist-info/entry_points.txt
debio-0.1.1.dist-info/top_level.txt
debio-0.1.1.dist-info/RECORD
