Metadata-Version: 2.1
Name: debio
Version: 0.1.1
Summary: A community-curated, decentralized biomedical ontology.
Home-page: https://github.com/biopragmatics/debio
Download-URL: https://github.com/biopragmatics/debio/releases
Author: Charles Tapley Hoyt
Author-email: cthoyt@gmail.com
Maintainer: Charles Tapley Hoyt
Maintainer-email: cthoyt@gmail.com
License: MIT
Project-URL: Bug Tracker, https://github.com/biopragmatics/debio/issues
Project-URL: Source Code, https://github.com/biopragmatics/debio
Keywords: snekpack,cookiecutter,ontology,biocuration,biosemantics,semantic web,systems biology,bioinformatics,cheminformatics,chemoinformatics,knowledge graphs
Classifier: Development Status :: 1 - Planning
Classifier: Environment :: Console
Classifier: Intended Audience :: Developers
Classifier: License :: OSI Approved :: MIT License
Classifier: Operating System :: OS Independent
Classifier: Framework :: Pytest
Classifier: Framework :: tox
Classifier: Framework :: Sphinx
Classifier: Programming Language :: Python
Classifier: Programming Language :: Python :: 3.8
Classifier: Programming Language :: Python :: 3.9
Classifier: Programming Language :: Python :: 3.10
Classifier: Programming Language :: Python :: 3 :: Only
Requires-Python: >=3.8
License-File: LICENSE
Requires-Dist: pyobo (>=0.8.3)
Provides-Extra: docs
Requires-Dist: sphinx ; extra == 'docs'
Requires-Dist: sphinx-rtd-theme ; extra == 'docs'
Requires-Dist: sphinx-autodoc-typehints ; extra == 'docs'
Requires-Dist: sphinx-automodapi ; extra == 'docs'
Provides-Extra: export
Requires-Dist: jinja2 ; extra == 'export'
Requires-Dist: bioontologies ; extra == 'export'
Provides-Extra: tests
Requires-Dist: pytest ; extra == 'tests'
Requires-Dist: coverage ; extra == 'tests'
